tralalalal/__init__.py
tralalalal/supersets.py
tralalalal-1.0.0.dist-info/WHEEL
tralalalal-1.0.0.dist-info/METADATA
tralalalal-1.0.0.dist-info/RECORD
